MANIFEST.in
README.rst
setup.py
apiplayground/__init__.py
apiplayground/constants.py
apiplayground/forms.py
apiplayground/models.py
apiplayground/playground.py
apiplayground/settings.py
apiplayground/utils.py
apiplayground/static/api_browser/css/h5bp.css
apiplayground/static/api_browser/css/screen.css
apiplayground/static/api_browser/js/app.js
apiplayground/static/api_browser/js/jquery-1.7.1.min.js
apiplayground/static/api_browser/js/jquery.class.min.js
apiplayground/static/api_browser/js/jquery.form2json.js
apiplayground/static/api_browser/js/jquery.rest-form.js
apiplayground/templates/api_browser/base.html
apiplayground/templates/api_browser/index.html
apiplayground/templatetags/__init__.py
apiplayground/templatetags/api_browser_tags.py
django_api_playground.egg-info/PKG-INFO
django_api_playground.egg-info/SOURCES.txt
django_api_playground.egg-info/dependency_links.txt
django_api_playground.egg-info/not-zip-safe
django_api_playground.egg-info/top_level.txt