Metadata-Version: 1.0
Name: django-api-playground
Version: 0.1.0
Summary: API Playground for RESTful APIs
Home-page: http://github.com/fatiherikli/django-api-playground
Author: fatiherikli
Author-email: fatiherikli@gmail.com
License: BSD
Platform: UNKNOWN
Classifier: Development Status :: 3 - Alpha
Classifier: Environment :: Web Environment
Classifier: Intended Audience :: Developers
Classifier: License :: OSI Approved :: BSD License
Classifier: Operating System :: OS Independent
Classifier: Programming Language :: Python
Classifier: Programming Language :: Python :: 2.7
Classifier: Framework :: Django
